aliyunsdkopenitag/__init__.py
aliyunsdkopenitag/request/__init__.py
aliyunsdkopenitag/request/v20220616/AddWorkNodeWorkforceRequest.py
aliyunsdkopenitag/request/v20220616/CreateTaskRequest.py
aliyunsdkopenitag/request/v20220616/CreateTemplateRequest.py
aliyunsdkopenitag/request/v20220616/CreateUserRequest.py
aliyunsdkopenitag/request/v20220616/DeleteTaskRequest.py
aliyunsdkopenitag/request/v20220616/DeleteTemplateRequest.py
aliyunsdkopenitag/request/v20220616/DeleteUserRequest.py
aliyunsdkopenitag/request/v20220616/ExportAnnotationsRequest.py
aliyunsdkopenitag/request/v20220616/GetJobRequest.py
aliyunsdkopenitag/request/v20220616/GetSubtaskItemRequest.py
aliyunsdkopenitag/request/v20220616/GetSubtaskRequest.py
aliyunsdkopenitag/request/v20220616/GetTaskRequest.py
aliyunsdkopenitag/request/v20220616/GetTaskStatisticsRequest.py
aliyunsdkopenitag/request/v20220616/GetTaskStatusRequest.py
aliyunsdkopenitag/request/v20220616/GetTaskTemplateQuestionsRequest.py
aliyunsdkopenitag/request/v20220616/GetTaskTemplateRequest.py
aliyunsdkopenitag/request/v20220616/GetTaskTemplateViewsRequest.py
aliyunsdkopenitag/request/v20220616/GetTaskWorkforceRequest.py
aliyunsdkopenitag/request/v20220616/GetTaskWorkforceStatisticRequest.py
aliyunsdkopenitag/request/v20220616/GetTemplateQuestionsRequest.py
aliyunsdkopenitag/request/v20220616/GetTemplateRequest.py
aliyunsdkopenitag/request/v20220616/GetTemplateViewRequest.py
aliyunsdkopenitag/request/v20220616/GetTenantRequest.py
aliyunsdkopenitag/request/v20220616/GetUserRequest.py
aliyunsdkopenitag/request/v20220616/ListJobsRequest.py
aliyunsdkopenitag/request/v20220616/ListSubtaskItemsRequest.py
aliyunsdkopenitag/request/v20220616/ListSubtasksRequest.py
aliyunsdkopenitag/request/v20220616/ListTasksRequest.py
aliyunsdkopenitag/request/v20220616/ListTemplatesRequest.py
aliyunsdkopenitag/request/v20220616/ListTenantsRequest.py
aliyunsdkopenitag/request/v20220616/ListUsersRequest.py
aliyun_python_sdk_openitag-1.0.0.dist-info/LICENSE
aliyun_python_sdk_openitag-1.0.0.dist-info/METADATA
aliyun_python_sdk_openitag-1.0.0.dist-info/WHEEL
aliyun_python_sdk_openitag-1.0.0.dist-info/top_level.txt
aliyun_python_sdk_openitag-1.0.0.dist-info/RECORD
